trollflow_sat/__init__.py
trollflow_sat/area_gatherer.py
trollflow_sat/compositor.py
trollflow_sat/coverage.py
trollflow_sat/enhance.py
trollflow_sat/fetch.py
trollflow_sat/resampler.py
trollflow_sat/satpy_compositor.py
trollflow_sat/satpy_coverage.py
trollflow_sat/satpy_resampler.py
trollflow_sat/satpy_writer.py
trollflow_sat/scene_loader.py
trollflow_sat/segment_gatherer.py
trollflow_sat/utils.py
trollflow_sat/version.py
trollflow_sat/writer.py
trollflow_sat-0.12.0.dist-info/METADATA
trollflow_sat-0.12.0.dist-info/RECORD
trollflow_sat-0.12.0.dist-info/WHEEL
trollflow_sat-0.12.0.dist-info/top_level.txt
