Metadata-Version: 2.1
Name: trollflow-sat
Version: 0.12.0
Summary: Pytroll workflow plugins for satellite data
Home-page: https://github.com/pytroll/trollflow-sat
Author: Panu Lahtinen
Author-email: panu.lahtinen@fmi.fi
License: UNKNOWN
Platform: UNKNOWN
Classifier: Development Status :: 3 - Alpha
Classifier: Intended Audience :: Science/Research
Classifier: License :: OSI Approved :: GNU General Public License v3 or later (GPLv3+)
Classifier: Operating System :: OS Independent
Classifier: Programming Language :: Python
Classifier: Topic :: Scientific/Engineering
Requires-Dist: trollflow
Requires-Dist: posttroll
Requires-Dist: trollsift
Requires-Dist: dpath
Requires-Dist: six
